datasette_debug_events.py
datasette_debug_events-0.1a2.dist-info/licenses/LICENSE
datasette_debug_events-0.1a2.dist-info/METADATA
datasette_debug_events-0.1a2.dist-info/WHEEL
datasette_debug_events-0.1a2.dist-info/entry_points.txt
datasette_debug_events-0.1a2.dist-info/top_level.txt
datasette_debug_events-0.1a2.dist-info/RECORD
