Metadata-Version: 2.4
Name: datasette-debug-events
Version: 0.1a2
Summary: Print Datasette events to standard error
Author: Simon Willison
License-Expression: Apache-2.0
Project-URL: Homepage, https://github.com/datasette/datasette-debug-events
Project-URL: Changelog, https://github.com/datasette/datasette-debug-events/releases
Project-URL: Issues, https://github.com/datasette/datasette-debug-events/issues
Project-URL: CI, https://github.com/datasette/datasette-debug-events/actions
Classifier: Framework :: Datasette
Requires-Python: >=3.10
License-File: LICENSE
Requires-Dist: datasette>=1.0a21
Provides-Extra: test
Requires-Dist: pytest; extra == "test"
Requires-Dist: pytest-asyncio; extra == "test"
Dynamic: license-file
